linear_regression/__init__.py
linear_regression/linear_regression.py
linear_regression_package_seds_lab3_meriem_terki-0.1.dist-info/LICENSE.txt
linear_regression_package_seds_lab3_meriem_terki-0.1.dist-info/METADATA
linear_regression_package_seds_lab3_meriem_terki-0.1.dist-info/WHEEL
linear_regression_package_seds_lab3_meriem_terki-0.1.dist-info/top_level.txt
linear_regression_package_seds_lab3_meriem_terki-0.1.dist-info/RECORD
