Metadata-Version: 2.1
Name: linear-regression-package-seds-lab3-meriem-terki
Version: 0.1
Summary: A simple linear regression model implemented from scratch
Author: Meriem Terki
Author-email: m.terki@esi.dz
Classifier: Programming Language :: Python :: 3
Classifier: License :: OSI Approved :: MIT License
Classifier: Operating System :: OS Independent
License-File: LICENSE.txt
Requires-Dist: numpy
